adversarial/__init__.py
adversarial/attack_generator.py
adversarial/counterfactual_generator.py
adversarial/module.py
adversarial/robustness_evaluator.py
core/__init__.py
core/evaluator.py
core/model_loader.py
linguallens/__init__.py
linguallens/adversarial/attack_generator.py
linguallens/adversarial/robustness_evaluator.py
linguallens/core/__init__.py
linguallens/core/evaluator.py
linguallens/core/linguallens.py
linguallens/core/model_comparison.py
linguallens/core/model_loader.py
linguallens/core/providers/__init__.py
linguallens/core/providers/anthropic_provider.py
linguallens/core/providers/base_provider.py
linguallens/core/providers/google_provider.py
linguallens/core/providers/huggingface_provider.py
linguallens/core/providers/openai_provider.py
linguallens/interpretability/llm_explainer.py
linguallens/utils/__init__.py
linguallens/utils/config.py
linguallens/utils/exceptions.py
linguallens/utils/logging_utils.py
linguallens/utils/text_utils.py
linguallens-0.1.0.dist-info/licenses/LICENSE
linguallens-0.1.0.dist-info/METADATA
linguallens-0.1.0.dist-info/WHEEL
linguallens-0.1.0.dist-info/top_level.txt
linguallens-0.1.0.dist-info/RECORD
