Metadata-Version: 2.4
Name: linguallens
Version: 0.1.0
Summary: A unified interface for interacting with language models from multiple providers
Home-page: https://github.com/linguallens/linguallens
Author: LingualLens Team
Author-email: LingualLens Team <info@linguallens.io>
License: MIT
Project-URL: Homepage, https://github.com/linguallens/linguallens
Project-URL: Bug Tracker, https://github.com/linguallens/linguallens/issues
Classifier: Programming Language :: Python :: 3
Classifier: Programming Language :: Python :: 3.8
Classifier: Programming Language :: Python :: 3.9
Classifier: Programming Language :: Python :: 3.10
Classifier: License :: OSI Approved :: MIT License
Classifier: Operating System :: OS Independent
Classifier: Development Status :: 3 - Alpha
Classifier: Intended Audience :: Developers
Classifier: Topic :: Scientific/Engineering :: Artificial Intelligence
Requires-Python: >=3.8
License-File: LICENSE
Requires-Dist: requests>=2.28.0
Requires-Dist: pyyaml>=6.0
Provides-Extra: openai
Requires-Dist: openai>=1.0.0; extra == "openai"
Provides-Extra: anthropic
Requires-Dist: anthropic>=0.5.0; extra == "anthropic"
Provides-Extra: google
Requires-Dist: google-generativeai>=0.2.0; extra == "google"
Provides-Extra: huggingface
Requires-Dist: transformers>=4.30.0; extra == "huggingface"
Requires-Dist: torch>=2.0.0; extra == "huggingface"
Provides-Extra: all
Requires-Dist: openai>=1.0.0; extra == "all"
Requires-Dist: anthropic>=0.5.0; extra == "all"
Requires-Dist: google-generativeai>=0.2.0; extra == "all"
Requires-Dist: transformers>=4.30.0; extra == "all"
Requires-Dist: torch>=2.0.0; extra == "all"
Provides-Extra: dev
Requires-Dist: pytest>=7.0.0; extra == "dev"
Requires-Dist: black>=23.0.0; extra == "dev"
Requires-Dist: isort>=5.10.0; extra == "dev"
Requires-Dist: flake8>=6.0.0; extra == "dev"
Requires-Dist: mypy>=1.0.0; extra == "dev"
Requires-Dist: build; extra == "dev"
Requires-Dist: twine; extra == "dev"
Dynamic: author
Dynamic: home-page
Dynamic: license-file
Dynamic: requires-python
